<?xml version="1.0" encoding="ISO-8859-2"?>
<!DOCTYPE tabela_kursow SYSTEM "abch.dtd">
<tabela_kursow typ="C">
   <numer_tabeli>239/C/NBP/2002</numer_tabeli>
   <data_notowania>2002-12-10</data_notowania>
   <data_publikacji>2002-12-11</data_publikacji>
   <pozycja>
      <nazwa_kraju>Australia</nazwa_kraju>
      <symbol_waluty>781</symbol_waluty>
      <przelicznik>1</przelicznik>
      <kod_waluty>AUD</kod_waluty>
      <kurs_kupna>2,1928</kurs_kupna>
      <kurs_sprzedazy>2,2372</kurs_sprzedazy>
   </pozycja>
   <pozycja>
      <nazwa_kraju>Czechy</nazwa_kraju>
      <symbol_waluty>213</symbol_waluty>
      <przelicznik>1</przelicznik>
      <kod_waluty>CZK</kod_waluty>
      <kurs_kupna>0,1267</kurs_kupna>
      <kurs_sprzedazy>0,1293</kurs_sprzedazy>
   </pozycja>
   <pozycja>
      <nazwa_kraju>Dania</nazwa_kraju>
      <symbol_waluty>792</symbol_waluty>
      <przelicznik>1</przelicznik>
      <kod_waluty>DKK</kod_waluty>
      <kurs_kupna>0,5309</kurs_kupna>
      <kurs_sprzedazy>0,5417</kurs_sprzedazy>
   </pozycja>
   <pozycja>
      <nazwa_kraju>Estonia</nazwa_kraju>
      <symbol_waluty>233</symbol_waluty>
      <przelicznik>1</przelicznik>
      <kod_waluty>EEK</kod_waluty>
      <kurs_kupna>0,2520</kurs_kupna>
      <kurs_sprzedazy>0,2570</kurs_sprzedazy>
   </pozycja>
   <pozycja>
      <nazwa_kraju>Japonia</nazwa_kraju>
      <symbol_waluty>784</symbol_waluty>
      <przelicznik>100</przelicznik>
      <kod_waluty>JPY</kod_waluty>
      <kurs_kupna>3,1642</kurs_kupna>
      <kurs_sprzedazy>3,2282</kurs_sprzedazy>
   </pozycja>
   <pozycja>
      <nazwa_kraju>Kanada</nazwa_kraju>
      <symbol_waluty>788</symbol_waluty>
      <przelicznik>1</przelicznik>
      <kod_waluty>CAD</kod_waluty>
      <kurs_kupna>2,5055</kurs_kupna>
      <kurs_sprzedazy>2,5561</kurs_sprzedazy>
   </pozycja>
   <pozycja>
      <nazwa_kraju>Norwegia</nazwa_kraju>
      <symbol_waluty>796</symbol_waluty>
      <przelicznik>1</przelicznik>
      <kod_waluty>NOK</kod_waluty>
      <kurs_kupna>0,5379</kurs_kupna>
      <kurs_sprzedazy>0,5487</kurs_sprzedazy>
   </pozycja>
   <pozycja>
      <nazwa_kraju>Szwajcaria</nazwa_kraju>
      <symbol_waluty>797</symbol_waluty>
      <przelicznik>1</przelicznik>
      <kod_waluty>CHF</kod_waluty>
      <kurs_kupna>2,6754</kurs_kupna>
      <kurs_sprzedazy>2,7294</kurs_sprzedazy>
   </pozycja>
   <pozycja>
      <nazwa_kraju>Szwecja</nazwa_kraju>
      <symbol_waluty>798</symbol_waluty>
      <przelicznik>1</przelicznik>
      <kod_waluty>SEK</kod_waluty>
      <kurs_kupna>0,4326</kurs_kupna>
      <kurs_sprzedazy>0,4414</kurs_sprzedazy>
   </pozycja>
   <pozycja>
      <nazwa_kraju>UGW</nazwa_kraju>
      <symbol_waluty>978</symbol_waluty>
      <przelicznik>1</przelicznik>
      <kod_waluty>EUR</kod_waluty>
      <kurs_kupna>3,9433</kurs_kupna>
      <kurs_sprzedazy>4,0229</kurs_sprzedazy>
   </pozycja>
   <pozycja>
      <nazwa_kraju>USA</nazwa_kraju>
      <symbol_waluty>787</symbol_waluty>
      <przelicznik>1</przelicznik>
      <kod_waluty>USD</kod_waluty>
      <kurs_kupna>3,9060</kurs_kupna>
      <kurs_sprzedazy>3,9850</kurs_sprzedazy>
   </pozycja>
   <pozycja>
      <nazwa_kraju>Wêgry</nazwa_kraju>
      <symbol_waluty>207</symbol_waluty>
      <przelicznik>100</przelicznik>
      <kod_waluty>HUF</kod_waluty>
      <kurs_kupna>1,6684</kurs_kupna>
      <kurs_sprzedazy>1,7022</kurs_sprzedazy>
   </pozycja>
   <pozycja>
      <nazwa_kraju>Wielka Brytania</nazwa_kraju>
      <symbol_waluty>789</symbol_waluty>
      <przelicznik>1</przelicznik>
      <kod_waluty>GBP</kod_waluty>
      <kurs_kupna>6,1436</kurs_kupna>
      <kurs_sprzedazy>6,2678</kurs_sprzedazy>
   </pozycja>
   <pozycja>
      <nazwa_kraju>MFW (SDR)</nazwa_kraju>
      <symbol_waluty>861</symbol_waluty>
      <przelicznik>1</przelicznik>
      <kod_waluty>XDR</kod_waluty>
      <kurs_kupna>5,2108</kurs_kupna>
      <kurs_sprzedazy>5,3160</kurs_sprzedazy>
   </pozycja>
</tabela_kursow>
